winzy_cut/__init__.py
winzy_cut-0.1.dist-info/LICENSE
winzy_cut-0.1.dist-info/METADATA
winzy_cut-0.1.dist-info/WHEEL
winzy_cut-0.1.dist-info/entry_points.txt
winzy_cut-0.1.dist-info/top_level.txt
winzy_cut-0.1.dist-info/RECORD
