Metadata-Version: 2.1
Name: winzy-cut
Version: 0.1
Summary: Mimics the functionality of the 'cut' command
Author: Sukhbinder Singh
License: Apache-2.0
Project-URL: Homepage, https://github.com/sukhbinder/winzy-cut
Project-URL: Changelog, https://github.com/sukhbinder/winzy-cut/releases
Project-URL: Issues, https://github.com/sukhbinder/winzy-cut/issues
Project-URL: CI, https://github.com/sukhbinder/winzy-cut/actions
Classifier: License :: OSI Approved :: Apache Software License
License-File: LICENSE
Requires-Dist: winzy
Provides-Extra: test
Requires-Dist: pytest ; extra == 'test'
